progressbar/widgets.py
progressbar/progressbar.py
progressbar/compat.py
progressbar/__init__.py
progressbar231-2.3.1.dist-info/RECORD
progressbar231-2.3.1.dist-info/metadata.json
progressbar231-2.3.1.dist-info/top_level.txt
progressbar231-2.3.1.dist-info/WHEEL
progressbar231-2.3.1.dist-info/METADATA
progressbar231-2.3.1.dist-info/DESCRIPTION.rst
